setup.py
activity_log/__init__.py
activity_log/admin.py
activity_log/conf.py
activity_log/middleware.py
activity_log/models.py
activity_log/router.py
activity_log/migrations/0001_initial.py
activity_log/migrations/0002_activitylog_ip_address.py
activity_log/migrations/0003_activitylog_extra_data.py
activity_log/migrations/__init__.py
django_user_activity_log.egg-info/PKG-INFO
django_user_activity_log.egg-info/SOURCES.txt
django_user_activity_log.egg-info/dependency_links.txt
django_user_activity_log.egg-info/top_level.txt