Metadata-Version: 1.1
Name: django-user-activity-log
Version: 0.0.8
Summary: HTTP queries logger with flexible filters.
Home-page: https://github.com/scailer/django-user-activity-log/
Author: Dmitriy Vlasov
Author-email: scailer@russia.ru
License: MIT license
Platform: UNKNOWN
Classifier: Framework :: Django
Classifier: Development Status :: 4 - Beta
Classifier: Environment :: Web Environment
Classifier: Intended Audience :: Developers
Classifier: License :: OSI Approved :: MIT License
Classifier: Programming Language :: Python
Classifier: Programming Language :: Python :: 2
Classifier: Programming Language :: Python :: 2.6
Classifier: Programming Language :: Python :: 2.7
Classifier: Topic :: Software Development :: Libraries :: Python Modules
